{
  "version": 1,
  "actions": [
    {
      "id": "cn-docx",
      "icon": "DocumentTextIcon",
      "color": "#2563EB",
      "skillMapping": "cn-docx",
      "prompts": [
        {
          "id": "docx-work-report"
        },
        {
          "id": "docx-meeting-minutes"
        },
        {
          "id": "docx-project-proposal"
        },
        {
          "id": "docx-summary"
        }
      ]
    },
    {
      "id": "data-analysis",
      "icon": "ChartBarIcon",
      "color": "#8B5CF6",
      "skillMapping": "xlsx",
      "prompts": [
        {
          "id": "excel-summary"
        },
        {
          "id": "image-to-excel"
        },
        {
          "id": "word-report"
        },
        {
          "id": "multi-excel-merge"
        }
      ]
    },
    {
      "id": "education",
      "icon": "AcademicCapIcon",
      "color": "#10B981",
      "skillMapping": "frontend-design",
      "prompts": [
        {
          "id": "edu-english-words"
        },
        {
          "id": "edu-math-explain"
        },
        {
          "id": "edu-essay-writing"
        },
        {
          "id": "edu-knowledge-explain"
        }
      ]
    }
  ]
}
